[
  {
    "code": "MVSD-673",
    "title": "MVSD-673 Gravure Idol Hot Spring Physical Interview. You Want To Be Famous, Right? Everyone Does This (lol) Riho Shishido",
    "source_url": "https://jable.tv/videos/mvsd-673/",
    "thumbnail_url": "https://assets-cdn.jable.tv/contents/videos_screenshots/56000/56349/preview.jpg",
    "thumbnail_original": "https://assets-cdn.jable.tv/contents/videos_screenshots/56000/56349/preview.jpg",
    "duration": "2:38:00",
    "hd_quality": true,
    "views": "9 814",
    "likes": "82",
    "release_date": "Released at 2026-01-15",
    "upload_time": "2026-01-23T14:24:50.953547",
    "processed_at": "2026-01-23T15:29:32.127365",
    "categories": [
      "Roleplay"
    ],
    "models": [
      "宍戸里帆"
    ],
    "tags": [
      "Girl",
      "Creampie",
      "Big tits",
      "Facial",
      "Short hair",
      "Tit Wank",
      "Kimono",
      "Hot spring"
    ],
    "preview_images": [
      "https://astin-cowing.mushroomtrack.com/hls/iVVmthgpp5-eUb-4KjCRGw/1769191879/56000/56349/thumbvtt.ts",
      "https://assets-cdn.jable.tv/contents/videos_screenshots/56000/56349/preview.jpg"
    ],
    "preview_video_url": "https://hglink.to/e/None",
    "preview_gif_url": null,
    "preview_duration": 80.0,
    "preview_clips": 60,
    "preview_file_size_mb": 27.543593406677246,
    "preview_generated": true,
    "hosting": {
      "streamwish": {
        "embed_url": "https://hglink.to/e/None",
        "watch_url": "https://hglink.to/None",
        "download_url": "https://hglink.to/None",
        "direct_url": "https://streamwish.com/None",
        "api_url": "https://api.streamwish.com/api/file/direct_link?key=31637q4gsnt23yyvd0or6&file_code=None",
        "filecode": null,
        "upload_time": 0,
        "uploaded_at": "2026-01-23T15:29:32.127551"
      }
    },
    "file_size": 0,
    "upload_folder": "JAV_VIDEOS/MVSD-673"
  }
]