[
  {
    "code": "SNOS-054",
    "title": "SNOS-054 -  Soa, a glamorous idol with a black bob and a slim waist, seems to want to be licked and violated by a perverted old man, down to every inch of her body.",
    "title_jp": null,
    "cover_url": "https://www.javdatabase.com/covers/full/sn/snos00054pl.webp",
    "screenshots": [
      "https://pics.dmm.co.jp/digital/video/snos00054/snos00054jp-1.jpg",
      "https://pics.dmm.co.jp/digital/video/snos00054/snos00054jp-2.jpg",
      "https://pics.dmm.co.jp/digital/video/snos00054/snos00054jp-3.jpg",
      "https://pics.dmm.co.jp/digital/video/snos00054/snos00054jp-4.jpg",
      "https://pics.dmm.co.jp/digital/video/snos00054/snos00054jp-5.jpg",
      "https://pics.dmm.co.jp/digital/video/snos00054/snos00054jp-6.jpg",
      "https://pics.dmm.co.jp/digital/video/snos00054/snos00054jp-7.jpg",
      "https://pics.dmm.co.jp/digital/video/snos00054/snos00054jp-8.jpg",
      "https://pics.dmm.co.jp/digital/video/snos00054/snos00054jp-9.jpg",
      "https://pics.dmm.co.jp/digital/video/snos00054/snos00054jp-10.jpg"
    ],
    "cast": [
      {
        "actress_name": "Soa",
        "actress_name_jp": "Soa",
        "actress_name_alt": null,
        "actress_image_url": "https://www.javdatabase.com/idolimages/full/soa.webp",
        "actress_age": null,
        "actress_birthdate": "2025-11-07",
        "actress_birthplace": null,
        "actress_height_cm": 165,
        "actress_shoe_size": null,
        "actress_bust_cm": null,
        "actress_waist_cm": null,
        "actress_hips_cm": null,
        "actress_cup_size": "F",
        "actress_hair_length": "Medium",
        "actress_hair_color": "Black",
        "actress_blood_type": null,
        "actress_zodiac_sign": null,
        "actress_debut_date": "2025-11-07",
        "actress_debut_age": null
      }
    ],
    "release_date": "2026-01-23",
    "duration": "2:51:28",
    "runtime_minutes": 170,
    "hd_quality": true,
    "file_size": 2352797926,
    "studio": "S1 NO.1 STYLE",
    "director": null,
    "label": null,
    "series": null,
    "categories": [
      "Pantyhose",
      "Sex Only"
    ],
    "genres": [
      "Exclusive",
      "Distribution",
      "Featured",
      "Actress",
      "Hi",
      "Def",
      "Kiss",
      "Kiss",
      "Nymphomaniac",
      "Orgasm",
      "Slender",
      "Threesome",
      "Foursome"
    ],
    "tags": [
      "Girl",
      "Big tits",
      "Short hair",
      "Pantyhose",
      "3P",
      "Beautiful leg",
      "Fishnets",
      "Kiss",
      "Stockings"
    ],
    "views": "10226",
    "likes": "176",
    "rating": null,
    "rating_count": null,
    "hosting": {
      "streamwish": {
        "embed_url": "https://hglink.to/e/wljekckt0vxh",
        "watch_url": "https://hglink.to/wljekckt0vxh",
        "download_url": "https://hglink.to/wljekckt0vxh",
        "direct_url": "https://streamwish.com/wljekckt0vxh",
        "api_url": "https://api.streamwish.com/api/file/direct_link?key=31637q4gsnt23yyvd0or6&file_code=wljekckt0vxh",
        "filecode": "wljekckt0vxh",
        "upload_time": 148.67591381072998,
        "uploaded_at": "2026-01-24T10:26:10.727480"
      }
    },
    "source_javdb": "https://www.javdatabase.com/movies/snos-054/",
    "source_jable": "https://jable.tv/videos/snos-054/",
    "javdb_available": true,
    "scraped_at": "2026-01-24T10:26:23.946434",
    "preview_ia": {
      "identifier": "javcore-preview-snos-054",
      "direct_url": "https://archive.org/download/javcore-preview-snos-054/SNOS-054_preview.mp4",
      "details_url": "https://archive.org/details/javcore-preview-snos-054",
      "filename": "SNOS-054_preview.mp4",
      "file_size_mb": 3.774350166320801,
      "uploaded_at": "2026-01-24T10:32:38.534296",
      "generated_at": "2026-01-24T10:32:38.534307"
    }
  },
  {
    "code": "SNOS-056",
    "title": "SNOS-056 -  A lewd weekend for a man and woman who crossed the line under the influence of alcohol in an ordinary everyday life. Raw and ordinary, but the most erotic sex. Ayaka Kawakita",
    "title_jp": null,
    "cover_url": "https://www.javdatabase.com/covers/full/sn/snos00056pl.webp",
    "screenshots": [
      "https://pics.dmm.co.jp/digital/video/snos00056/snos00056jp-1.jpg",
      "https://pics.dmm.co.jp/digital/video/snos00056/snos00056jp-2.jpg",
      "https://pics.dmm.co.jp/digital/video/snos00056/snos00056jp-3.jpg",
      "https://pics.dmm.co.jp/digital/video/snos00056/snos00056jp-4.jpg",
      "https://pics.dmm.co.jp/digital/video/snos00056/snos00056jp-5.jpg",
      "https://pics.dmm.co.jp/digital/video/snos00056/snos00056jp-6.jpg",
      "https://pics.dmm.co.jp/digital/video/snos00056/snos00056jp-7.jpg",
      "https://pics.dmm.co.jp/digital/video/snos00056/snos00056jp-8.jpg",
      "https://pics.dmm.co.jp/digital/video/snos00056/snos00056jp-9.jpg",
      "https://pics.dmm.co.jp/digital/video/snos00056/snos00056jp-10.jpg"
    ],
    "cast": [
      {
        "actress_name": "Saika Kawakita",
        "actress_name_jp": "河北彩花",
        "actress_name_alt": null,
        "actress_image_url": "https://www.javdatabase.com/idolimages/full/saika-kawakita.webp",
        "actress_age": 26,
        "actress_birthdate": "1999",
        "actress_birthplace": "Chiba",
        "actress_height_cm": 169,
        "actress_shoe_size": null,
        "actress_bust_cm": null,
        "actress_waist_cm": null,
        "actress_hips_cm": null,
        "actress_cup_size": "E",
        "actress_hair_length": "Long",
        "actress_hair_color": "Black, Brown",
        "actress_blood_type": null,
        "actress_zodiac_sign": "Sagittarius,",
        "actress_debut_date": "2018-04-14",
        "actress_debut_age": 19
      }
    ],
    "release_date": "2026-01-23",
    "duration": "2:05:10",
    "runtime_minutes": 125,
    "hd_quality": true,
    "file_size": 1274655189,
    "studio": "S1 NO.1 STYLE",
    "director": null,
    "label": null,
    "series": null,
    "categories": [
      "Roleplay"
    ],
    "genres": [
      "Beautiful",
      "Tits",
      "Blowjob",
      "Cowgirl",
      "Drama",
      "Exclusive",
      "Distribution",
      "Featured",
      "Actress",
      "Hi",
      "Def",
      "Kiss",
      "Kiss"
    ],
    "tags": [
      "Girl",
      "Short hair",
      "Kiss",
      "Blowjob"
    ],
    "views": "933",
    "likes": "96",
    "rating": null,
    "rating_count": null,
    "hosting": {
      "streamwish": {
        "embed_url": "https://hglink.to/e/odv8wd2f71jt",
        "watch_url": "https://hglink.to/odv8wd2f71jt",
        "download_url": "https://hglink.to/odv8wd2f71jt",
        "direct_url": "https://streamwish.com/odv8wd2f71jt",
        "api_url": "https://api.streamwish.com/api/file/direct_link?key=31637q4gsnt23yyvd0or6&file_code=odv8wd2f71jt",
        "filecode": "odv8wd2f71jt",
        "upload_time": 66.89429473876953,
        "uploaded_at": "2026-01-24T10:50:59.822911"
      }
    },
    "source_javdb": "https://www.javdatabase.com/movies/snos-056/",
    "source_jable": "https://jable.tv/videos/snos-056/",
    "javdb_available": true,
    "scraped_at": "2026-01-24T10:51:13.107077"
  }
]