{
  "total_videos": 5,
  "total_size_bytes": 7663180364,
  "by_hosting": {
    "streamwish": 4,
    "streamtape": 1
  },
  "by_category": {
    "Roleplay": 5,
    "BDSM": 3,
    "Insult": 1,
    "Group Sex": 2,
    "Chinese Subtitle": 2,
    "Uniform": 2,
    "Pantyhose": 1
  },
  "by_model": {
    "宍戸里帆": 1,
    "稲森美優": 1,
    "MINAMO": 1,
    "水原わこ": 1
  },
  "by_studio": {
    "Real Works": 1
  },
  "with_javdb": 1,
  "with_cast": 1,
  "with_screenshots": 1,
  "last_updated": "2026-01-23T18:19:12.389802"
}